llm_acuration/__init__.py
llm_acuration/hello.py
llm_acuration-0.0.6.dist-info/LICENSE.txt
llm_acuration-0.0.6.dist-info/METADATA
llm_acuration-0.0.6.dist-info/WHEEL
llm_acuration-0.0.6.dist-info/top_level.txt
llm_acuration-0.0.6.dist-info/RECORD
