Metadata-Version: 2.1
Name: llm_acuration
Version: 0.0.6
Summary: An LLM package made by Acuration
Author-email: LLM Acuration team <cuboidrandom@gmail.com>
Classifier: Programming Language :: Python :: 3
Classifier: License :: OSI Approved :: MIT License
Classifier: Operating System :: OS Independent
Requires-Python: >=3.8
License-File: LICENSE.txt
Requires-Dist: flask
